Metadata-Version: 1.0
Name: mafan-traditional
Version: 1.0.0
Summary: A traditional dictionary for use with Mafan
Home-page: https://github.com/hermanschaaf/mafan_traditional
Author: Herman Schaaf
Author-email: herman@ironzebra.com
License: LICENSE.txt
Platform: UNKNOWN
